synfinary/__init__.py
synfinary/bincrypt.py
synfinary/binify.py
synfinary-0.5.dist-info/METADATA
synfinary-0.5.dist-info/WHEEL
synfinary-0.5.dist-info/top_level.txt
synfinary-0.5.dist-info/RECORD
