Metadata-Version: 2.1
Name: synfinary
Version: 0.5
Summary: Text to binary
Author: synfosec
Author-email: <NULLNULLNULL@NULL.NULL>
Classifier: Programming Language :: Python :: 3
Classifier: Operating System :: Unix
Classifier: Operating System :: MacOS :: MacOS X
Classifier: Operating System :: Microsoft :: Windows
